punic/__init__.py
punic/punic.py
punictest-0.1.1.dist-info/LICENSE
punictest-0.1.1.dist-info/METADATA
punictest-0.1.1.dist-info/WHEEL
punictest-0.1.1.dist-info/top_level.txt
punictest-0.1.1.dist-info/RECORD
