Metadata-Version: 2.1
Name: punictest
Version: 0.1.1
Summary: Simple unit testing for python
Home-page: https://github.com/Somespi/Punic
Author: Someone.
Author-email: someonegithub@email.com
Keywords: unit testing test automation quality assurance software development
Classifier: Development Status :: 3 - Alpha
Classifier: License :: OSI Approved :: MIT License
Classifier: Programming Language :: Python :: 3
Classifier: Programming Language :: Python :: 3.6
Classifier: Programming Language :: Python :: 3.7
Classifier: Programming Language :: Python :: 3.8
License-File: LICENSE
